keycloak/__init__.py
keycloak/connection.py
keycloak/exceptions.py
keycloak/keycloak_admin.py
keycloak/keycloak_openid.py
keycloak/urls_patterns.py
keycloak/authorization/__init__.py
keycloak/authorization/permission.py
keycloak/authorization/policy.py
keycloak/authorization/role.py
keycloak/tests/__init__.py
keycloak/tests/test_connection.py
py_keycloak-0.0.1.6.dist-info/METADATA
py_keycloak-0.0.1.6.dist-info/RECORD
py_keycloak-0.0.1.6.dist-info/WHEEL
py_keycloak-0.0.1.6.dist-info/top_level.txt
