Metadata-Version: 2.1
Name: py-keycloak
Version: 0.0.1.6
Summary: py-keycloak is a Python package providing access to the Keycloak API.
Home-page: https://github.com/c0mpiler/py-keycloak
Author: c0mpiler
Author-email: c0mpiler@outlook.com
License: Apache License 2.0
Keywords: keycloak openid
Platform: UNKNOWN
Classifier: Programming Language :: Python :: 3.5
Classifier: Programming Language :: Python :: 3.6
Classifier: License :: OSI Approved :: Apache Software License
Classifier: Development Status :: 3 - Alpha
Classifier: Topic :: Utilities
Classifier: Intended Audience :: Developers
Classifier: Natural Language :: English
Requires-Dist: requests (==2.18.4)
Requires-Dist: httmock (==1.2.5)
Requires-Dist: python-jose (==1.4.0)
